LICENSE.txt
README.md
setup.py
wifi_wrapper/__init__.py
wifi_wrapper/subprocess_wrapper.py
wifi_wrapper/wifi.py
wifi_wrapper.egg-info/PKG-INFO
wifi_wrapper.egg-info/SOURCES.txt
wifi_wrapper.egg-info/dependency_links.txt
wifi_wrapper.egg-info/top_level.txt