Metadata-Version: 2.1
Name: wifi-wrapper
Version: 0.1.0
Summary: A python wrapper over nmcli tool for linux devices.
Home-page: https://github.com/hrithik098/wifi_wrapper
Author: Hrithik Yadav
Author-email: hrithiky328@gmail.com
License: MIT
Download-URL: https://github.com/hrithik098/wifi_wrapper/archive/refs/tags/0.1.0.tar.gz
Project-URL: Bug Tracker, https://github.com/hrithik098/wifi_wrapper/issues
Keywords: pypi,nmcli,wifi tools
Platform: UNKNOWN
Classifier: Intended Audience :: Developers
Classifier: License :: OSI Approved :: MIT License
Classifier: Programming Language :: Python :: 3.9
